online_monitor/OnlineMonitor.ini
online_monitor/OnlineMonitor.py
online_monitor/__init__.py
online_monitor/configuration.yaml
online_monitor/plugin_online_monitor.py
online_monitor/start_converter.py
online_monitor/start_online_monitor.py
online_monitor/start_producer_sim.py
online_monitor/stop_online_monitor.py
online_monitor/converter/__init__.py
online_monitor/converter/converter_manager.py
online_monitor/converter/forwarder.py
online_monitor/converter/transceiver.py
online_monitor/examples/Readme
online_monitor/examples/__init__.py
online_monitor/examples/configuration.yaml
online_monitor/examples/converter/bidirectional_converter.py
online_monitor/examples/converter/example_converter.py
online_monitor/examples/producer_sim/example_producer_sim.py
online_monitor/examples/producer_sim/silab_default_producer.py
online_monitor/examples/receiver/bidirectional_receiver.py
online_monitor/examples/receiver/example_receiver.py
online_monitor/receiver/__init__.py
online_monitor/receiver/receiver.py
online_monitor/testing/__init__.py
online_monitor/testing/test_converter.py
online_monitor/testing/test_online_monitor.py
online_monitor/testing/test_producer_sim.py
online_monitor/testing/test_serialization.py
online_monitor/testing/test_settings.py
online_monitor/testing/test_start_scripts.py
online_monitor/testing/test_utils.py
online_monitor/utils/__init__.py
online_monitor/utils/producer_sim.py
online_monitor/utils/producer_sim_manager.py
online_monitor/utils/settings.py
online_monitor/utils/utils.py
online_monitor-0.6.0.dist-info/LICENSE
online_monitor-0.6.0.dist-info/METADATA
online_monitor-0.6.0.dist-info/WHEEL
online_monitor-0.6.0.dist-info/entry_points.txt
online_monitor-0.6.0.dist-info/top_level.txt
online_monitor-0.6.0.dist-info/RECORD
