Metadata-Version: 2.1
Name: online-monitor
Version: 0.6.0
Summary: A generic online monitor showing real-time plots from multiple independent data acquisition systems.
Home-page: https://github.com/SiLab-Bonn/online_monitor
Author: David-Leon Pohl
Author-email: pohl@physik.uni-bonn.de
Maintainer: Pascal Wolf
Maintainer-email: wolf@physik.uni-bonn.de
License: MIT License
Keywords: online monitor,real time,plots
Platform: any
Requires-Dist: pyzmq
Requires-Dist: pyyaml
Requires-Dist: psutil
Requires-Dist: pyqtgraph (>=0.13)
Requires-Dist: pyqt5 (==5.15.2)
Requires-Dist: pytest
Requires-Dist: matplotlib
Requires-Dist: testfixtures
